{
  "annotations": {
    "list": [
      {
        "builtIn": 1,
        "datasource": "-- Grafana --",
        "enable": true,
        "hide": true,
        "iconColor": "rgba(0, 211, 255, 1)",
        "name": "Annotations & Alerts",
        "type": "dashboard"
      }
    ]
  },
  "description": "",
  "editable": true,
  "gnetId": null,
  "graphTooltip": 0,
  "id": 5,
  "iteration": 1593514430385,
  "links": [],
  "panels": [
    {
      "content": "\n# <p style=\"text-align: center;\"> ${index_title} </p>\n\n## <p style=\"text-align: center;\"> ${index_description} </p>\n\n________\n\n### <p style=\"text-align: center;\">  ${index_formula} </p>\n",
      "datasource": null,
      "description": "",
      "fieldConfig": {
        "defaults": {
          "custom": {}
        },
        "overrides": []
      },
      "gridPos": {
        "h": 5,
        "w": 24,
        "x": 0,
        "y": 0
      },
      "id": 2,
      "mode": "markdown",
      "targets": [
        {
          "format": "time_series",
          "group": [],
          "metricColumn": "none",
          "rawQuery": false,
          "rawSql": "SELECT\n  $__time(time_column),\n  value1\nFROM\n  metric_table\nWHERE\n  $__timeFilter(time_column)\n",
          "refId": "A",
          "select": [
            [
              {
                "params": [
                  "value"
                ],
                "type": "column"
              }
            ]
          ],
          "timeColumn": "time",
          "where": [
            {
              "name": "$__timeFilter",
              "params": [],
              "type": "macro"
            }
          ]
        }
      ],
      "timeFrom": null,
      "timeShift": null,
      "title": "",
      "type": "text"
    },
    {
      "datasource": null,
      "fieldConfig": {
        "defaults": {
          "custom": {
            "align": "center",
            "displayMode": "auto"
          },
          "mappings": [],
          "thresholds": {
            "mode": "absolute",
            "steps": [
              {
                "color": "dark-green",
                "value": null
              },
              {
                "color": "dark-red",
                "value": 0
              },
              {
                "color": "dark-orange",
                "value": 15
              },
              {
                "color": "dark-yellow",
                "value": 40
              },
              {
                "color": "dark-green",
                "value": 60
              }
            ]
          },
          "unit": "percent"
        },
        "overrides": [
          {
            "matcher": {
              "id": "byName",
              "options": "low"
            },
            "properties": [
              {
                "id": "custom.displayMode",
                "value": "lcd-gauge"
              }
            ]
          },
          {
            "matcher": {
              "id": "byName",
              "options": "high"
            },
            "properties": [
              {
                "id": "custom.displayMode",
                "value": "lcd-gauge"
              }
            ]
          }
        ]
      },
      "gridPos": {
        "h": 7,
        "w": 7,
        "x": 0,
        "y": 5
      },
      "id": 10,
      "options": {
        "showHeader": false
      },
      "pluginVersion": "7.0.4",
      "repeat": null,
      "repeatDirection": "h",
      "targets": [
        {
          "format": "table",
          "group": [],
          "hide": false,
          "metricColumn": "none",
          "rawQuery": true,
          "rawSql": "select * from json_to_recordset(\n  '${index_classes}'\n) as t(low float, high float, value text, color text) order by low\n\n",
          "refId": "A",
          "select": [
            [
              {
                "params": [
                  "value"
                ],
                "type": "column"
              }
            ]
          ],
          "timeColumn": "time",
          "where": [
            {
              "name": "$__timeFilter",
              "params": [],
              "type": "macro"
            }
          ]
        }
      ],
      "timeFrom": null,
      "timeShift": null,
      "title": "Legend",
      "transformations": [
        {
          "id": "organize",
          "options": {
            "excludeByName": {
              "color": true
            },
            "indexByName": {},
            "renameByName": {}
          }
        }
      ],
      "type": "table"
    },
    {
      "datasource": null,
      "description": "",
      "fieldConfig": {
        "defaults": {
          "custom": {},
          "mappings": [],
          "thresholds": {
            "mode": "absolute",
            "steps": [
              {
                "color": "dark-green",
                "value": null
              },
              {
                "color": "dark-red",
                "value": 0
              },
              {
                "color": "dark-orange",
                "value": 15
              },
              {
                "color": "dark-yellow",
                "value": 40
              },
              {
                "color": "dark-green",
                "value": 60
              }
            ]
          },
          "unit": "percent"
        },
        "overrides": []
      },
      "gridPos": {
        "h": 7,
        "w": 7,
        "x": 7,
        "y": 5
      },
      "id": 12,
      "options": {
        "orientation": "auto",
        "reduceOptions": {
          "calcs": [
            "mean"
          ],
          "fields": "",
          "values": false
        },
        "showThresholdLabels": false,
        "showThresholdMarkers": true
      },
      "pluginVersion": "7.0.4",
      "targets": [
        {
          "format": "table",
          "group": [],
          "metricColumn": "none",
          "rawQuery": true,
          "rawSql": "select \"${index_metric}\" from \"${Schema}\".\"${Index}\"  where \"año\"=${Year}\n",
          "refId": "A",
          "select": [
            [
              {
                "params": [
                  "value"
                ],
                "type": "column"
              }
            ]
          ],
          "timeColumn": "time",
          "where": [
            {
              "name": "$__timeFilter",
              "params": [],
              "type": "macro"
            }
          ]
        }
      ],
      "timeFrom": null,
      "timeShift": null,
      "title": "${index_metric} - ${Year}",
      "type": "gauge"
    },
    {
      "aliasColors": {},
      "bars": false,
      "dashLength": 10,
      "dashes": false,
      "datasource": "GaliciaSustentable",
      "fieldConfig": {
        "defaults": {
          "custom": {}
        },
        "overrides": []
      },
      "fill": 1,
      "fillGradient": 0,
      "gridPos": {
        "h": 7,
        "w": 10,
        "x": 14,
        "y": 5
      },
      "hiddenSeries": false,
      "id": 6,
      "legend": {
        "avg": false,
        "current": false,
        "max": false,
        "min": false,
        "show": true,
        "total": false,
        "values": false
      },
      "lines": true,
      "linewidth": 1,
      "nullPointMode": "null",
      "options": {
        "dataLinks": []
      },
      "percentage": false,
      "pointradius": 2,
      "points": false,
      "renderer": "flot",
      "seriesOverrides": [],
      "spaceLength": 10,
      "stack": false,
      "steppedLine": false,
      "targets": [
        {
          "format": "table",
          "group": [],
          "metricColumn": "evaluation",
          "rawQuery": true,
          "rawSql": "SELECT\n  TO_TIMESTAMP(\"año\"::text, 'YYYY') as \"time\",\n  \"${index_metric}\"\nFROM \"${Index}\"\nORDER BY 1,2\n",
          "refId": "A",
          "select": [
            [
              {
                "params": [
                  "\"Autocontención laboral\""
                ],
                "type": "column"
              }
            ]
          ],
          "table": "\"03 Autocontencion laboral evaluated\"",
          "timeColumn": "\"año\"",
          "timeColumnType": "int8",
          "where": [
            {
              "name": "$__unixEpochFilter",
              "params": [],
              "type": "macro"
            }
          ]
        }
      ],
      "thresholds": [
        {
          "colorMode": "custom",
          "fill": false,
          "fillColor": "#C4162A",
          "line": true,
          "lineColor": "#C4162A",
          "op": "lt",
          "value": 15,
          "yaxis": "right"
        },
        {
          "colorMode": "custom",
          "fill": false,
          "fillColor": "#FA6400",
          "line": true,
          "lineColor": "#FA6400",
          "op": "lt",
          "value": 40,
          "yaxis": "right"
        },
        {
          "colorMode": "custom",
          "fill": false,
          "fillColor": "#E0B400",
          "line": true,
          "lineColor": "#E0B400",
          "op": "lt",
          "value": 60,
          "yaxis": "right"
        },
        {
          "colorMode": "custom",
          "fill": false,
          "fillColor": "#37872D",
          "line": true,
          "lineColor": "#37872D",
          "op": "lt",
          "value": 100,
          "yaxis": "right"
        }
      ],
      "timeFrom": null,
      "timeRegions": [],
      "timeShift": null,
      "title": "Tendencia",
      "tooltip": {
        "shared": true,
        "sort": 0,
        "value_type": "individual"
      },
      "type": "graph",
      "xaxis": {
        "buckets": null,
        "mode": "time",
        "name": null,
        "show": true,
        "values": []
      },
      "yaxes": [
        {
          "format": "short",
          "label": null,
          "logBase": 1,
          "max": null,
          "min": null,
          "show": true
        },
        {
          "format": "short",
          "label": null,
          "logBase": 1,
          "max": null,
          "min": null,
          "show": true
        }
      ],
      "yaxis": {
        "align": false,
        "alignLevel": null
      }
    },
    {
      "datasource": null,
      "fieldConfig": {
        "defaults": {
          "custom": {
            "align": null
          },
          "mappings": [],
          "thresholds": {
            "mode": "absolute",
            "steps": [
              {
                "color": "green",
                "value": null
              },
              {
                "color": "red",
                "value": 80
              }
            ]
          }
        },
        "overrides": []
      },
      "gridPos": {
        "h": 7,
        "w": 24,
        "x": 0,
        "y": 12
      },
      "id": 14,
      "options": {
        "showHeader": true
      },
      "pluginVersion": "7.0.4",
      "targets": [
        {
          "format": "table",
          "group": [],
          "metricColumn": "none",
          "rawQuery": true,
          "rawSql": "select * from \"${Schema}\".\"${Index}\"\n",
          "refId": "A",
          "select": [
            [
              {
                "params": [
                  "value"
                ],
                "type": "column"
              }
            ]
          ],
          "timeColumn": "time",
          "where": [
            {
              "name": "$__timeFilter",
              "params": [],
              "type": "macro"
            }
          ]
        }
      ],
      "timeFrom": null,
      "timeShift": null,
      "title": "Datos completos",
      "type": "table"
    }
  ],
  "refresh": false,
  "schemaVersion": 25,
  "style": "dark",
  "tags": [],
  "templating": {
    "list": [
      {
        "allValue": null,
        "current": {
          "selected": false,
          "text": "public",
          "value": "public"
        },
        "datasource": "GaliciaSustentable",
        "definition": "SELECT\n\tschema_name\nFROM\n\tinformation_schema.schemata\nWHERE\n\tschema_name !~ '^(pg_)' AND\n\tschema_name != 'information_schema' AND\n\tschema_name != 'topology' AND\n\tschema_name != 'cron'\n",
        "hide": 0,
        "includeAll": false,
        "label": "Proyecto",
        "multi": false,
        "name": "Schema",
        "options": [
          {
            "selected": true,
            "text": "public",
            "value": "public"
          }
        ],
        "query": "SELECT\n\tschema_name\nFROM\n\tinformation_schema.schemata\nWHERE\n\tschema_name !~ '^(pg_)' AND\n\tschema_name != 'information_schema' AND\n\tschema_name != 'topology' AND\n\tschema_name != 'cron'\n",
        "refresh": 0,
        "regex": "",
        "skipUrlSync": false,
        "sort": 0,
        "tagValuesQuery": "",
        "tags": [],
        "tagsQuery": "",
        "type": "query",
        "useTags": false
      },
      {
        "allValue": null,
        "current": {
          "selected": false,
          "text": "2016",
          "value": "2016"
        },
        "datasource": "GaliciaSustentable",
        "definition": "select distinct(\"año\")::integer from \"${Schema}\".\"${Index}\"",
        "hide": 0,
        "includeAll": false,
        "label": "Año",
        "multi": false,
        "name": "Year",
        "options": [
          {
            "selected": false,
            "text": "2016",
            "value": "2016"
          },
          {
            "selected": false,
            "text": "2015",
            "value": "2015"
          },
          {
            "selected": true,
            "text": "2013",
            "value": "2013"
          },
          {
            "selected": false,
            "text": "2011",
            "value": "2011"
          }
        ],
        "query": "select distinct(\"año\")::integer from \"${Schema}\".\"${Index}\"",
        "refresh": 0,
        "regex": "",
        "skipUrlSync": false,
        "sort": 4,
        "tagValuesQuery": "",
        "tags": [],
        "tagsQuery": "",
        "type": "query",
        "useTags": false
      },
      {
        "allValue": null,
        "current": {
          "selected": false,
          "text": "03 Autocontencion laboral evaluated",
          "value": "03 Autocontencion laboral evaluated"
        },
        "datasource": "GaliciaSustentable",
        "definition": "SELECT\n\t table_name\nFROM\n\tinformation_schema.tables\nWHERE\n\ttable_schema = '${Schema}' AND\n\ttable_type = 'BASE TABLE' AND\n        table_name ~ '^(0|1|A|B|Theme)'\n",
        "hide": 0,
        "includeAll": false,
        "label": "Indice",
        "multi": false,
        "name": "Index",
        "options": [
          {
            "selected": false,
            "text": "00_PoboacionTotal qgis",
            "value": "00_PoboacionTotal qgis"
          },
          {
            "selected": false,
            "text": "01 Travellers percentage evaluated",
            "value": "01 Travellers percentage evaluated"
          },
          {
            "selected": false,
            "text": "01_Viajeros qgis",
            "value": "01_Viajeros qgis"
          },
          {
            "selected": false,
            "text": "02 Repeater travellers percentage evaluated",
            "value": "02 Repeater travellers percentage evaluated"
          },
          {
            "selected": false,
            "text": "02_ViajerosRepiten qgis",
            "value": "02_ViajerosRepiten qgis"
          },
          {
            "selected": true,
            "text": "03 Autocontencion laboral evaluated",
            "value": "03 Autocontencion laboral evaluated"
          },
          {
            "selected": false,
            "text": "03_AutocontencionLaboral qgis",
            "value": "03_AutocontencionLaboral qgis"
          },
          {
            "selected": false,
            "text": "04 Saldo migratorio percentage evaluated",
            "value": "04 Saldo migratorio percentage evaluated"
          },
          {
            "selected": false,
            "text": "04_SaldoMigratorio qgis",
            "value": "04_SaldoMigratorio qgis"
          },
          {
            "selected": false,
            "text": "05 Life expectancy at birth evaluated",
            "value": "05 Life expectancy at birth evaluated"
          },
          {
            "selected": false,
            "text": "05_EsperanzaVida qgis",
            "value": "05_EsperanzaVida qgis"
          },
          {
            "selected": false,
            "text": "06 Medical care capacity percentage evaluated",
            "value": "06 Medical care capacity percentage evaluated"
          },
          {
            "selected": false,
            "text": "06_CapacidadAtencionPrimaria qgis",
            "value": "06_CapacidadAtencionPrimaria qgis"
          },
          {
            "selected": false,
            "text": "07 Proximity evaluated",
            "value": "07 Proximity evaluated"
          },
          {
            "selected": false,
            "text": "07.1 Proximity areas",
            "value": "07.1 Proximity areas"
          },
          {
            "selected": false,
            "text": "07_PoboacionDistritoCensal qgis",
            "value": "07_PoboacionDistritoCensal qgis"
          },
          {
            "selected": false,
            "text": "A - Evaluation \"Atractivo de la ciudad\"",
            "value": "A - Evaluation \"Atractivo de la ciudad\""
          },
          {
            "selected": false,
            "text": "B - Evaluation \"Atractivo de la ciudad\"",
            "value": "B - Evaluation \"Atractivo de la ciudad\""
          },
          {
            "selected": false,
            "text": "Theme 1 synthesis",
            "value": "Theme 1 synthesis"
          }
        ],
        "query": "SELECT\n\t table_name\nFROM\n\tinformation_schema.tables\nWHERE\n\ttable_schema = '${Schema}' AND\n\ttable_type = 'BASE TABLE' AND\n        table_name ~ '^(0|1|A|B|Theme)'\n",
        "refresh": 0,
        "regex": "",
        "skipUrlSync": false,
        "sort": 1,
        "tagValuesQuery": "",
        "tags": [],
        "tagsQuery": "",
        "type": "query",
        "useTags": false
      },
      {
        "allValue": null,
        "current": {
          "selected": false,
          "text": "03 Autocontencion laboral",
          "value": "03 Autocontencion laboral"
        },
        "datasource": "GaliciaSustentable",
        "definition": "select display_name from indexes_metadata where index_table_name = '${Index}'",
        "hide": 2,
        "includeAll": false,
        "label": null,
        "multi": false,
        "name": "index_title",
        "options": [
          {
            "selected": true,
            "text": "03 Autocontencion laboral",
            "value": "03 Autocontencion laboral"
          }
        ],
        "query": "select display_name from indexes_metadata where index_table_name = '${Index}'",
        "refresh": 0,
        "regex": "",
        "skipUrlSync": false,
        "sort": 0,
        "tagValuesQuery": "",
        "tags": [],
        "tagsQuery": "",
        "type": "query",
        "useTags": false
      },
      {
        "allValue": null,
        "current": {
          "selected": false,
          "text": "Definición: Proporción de poboación do concello que traballa no mesmo ",
          "value": "Definición: Proporción de poboación do concello que traballa no mesmo "
        },
        "datasource": "GaliciaSustentable",
        "definition": "select description from indexes_metadata where index_table_name = '${Index}'",
        "hide": 2,
        "includeAll": false,
        "label": null,
        "multi": false,
        "name": "index_description",
        "options": [
          {
            "selected": true,
            "text": "Definición: Proporción de poboación do concello que traballa no mesmo ",
            "value": "Definición: Proporción de poboación do concello que traballa no mesmo "
          }
        ],
        "query": "select description from indexes_metadata where index_table_name = '${Index}'",
        "refresh": 0,
        "regex": "",
        "skipUrlSync": false,
        "sort": 0,
        "tagValuesQuery": "",
        "tags": [],
        "tagsQuery": "",
        "type": "query",
        "useTags": false
      },
      {
        "allValue": null,
        "current": {
          "selected": false,
          "text": "Fórmula: [Nº de afiliaciones en situación de alta laboral en la\nSeguridad Social de personas que trabajan en su municipio de residencia / Nº de\nafiliaciones en situación de alta laboral en la Seguridad Social de personas\nque residen no concello] * 100",
          "value": "Fórmula: [Nº de afiliaciones en situación de alta laboral en la\nSeguridad Social de personas que trabajan en su municipio de residencia / Nº de\nafiliaciones en situación de alta laboral en la Seguridad Social de personas\nque residen no concello] * 100"
        },
        "datasource": "GaliciaSustentable",
        "definition": "select formula from indexes_metadata where index_table_name = '${Index}'",
        "hide": 2,
        "includeAll": false,
        "label": null,
        "multi": false,
        "name": "index_formula",
        "options": [
          {
            "selected": true,
            "text": "Fórmula: [Nº de afiliaciones en situación de alta laboral en la\nSeguridad Social de personas que trabajan en su municipio de residencia / Nº de\nafiliaciones en situación de alta laboral en la Seguridad Social de personas\nque residen no concello] * 100",
            "value": "Fórmula: [Nº de afiliaciones en situación de alta laboral en la\nSeguridad Social de personas que trabajan en su municipio de residencia / Nº de\nafiliaciones en situación de alta laboral en la Seguridad Social de personas\nque residen no concello] * 100"
          }
        ],
        "query": "select formula from indexes_metadata where index_table_name = '${Index}'",
        "refresh": 0,
        "regex": "",
        "skipUrlSync": false,
        "sort": 0,
        "tagValuesQuery": "",
        "tags": [],
        "tagsQuery": "",
        "type": "query",
        "useTags": false
      },
      {
        "allValue": null,
        "current": {
          "selected": false,
          "text": "[\n    {\n        \"low\": 0,\n        \"high\": 15,\n        \"value\": \"Bajo\",\n        \"color\": \"dark-red\"\n    },\n    {\n        \"low\": 15,\n        \"high\": 40,\n        \"value\": \"Medio\",\n        \"color\": \"dark-orange\"\n    },\n    {\n        \"low\": 40,\n        \"high\": 60,\n        \"value\": \"Alto\",\n        \"color\": \"dark-yellow\"\n    },\n    {\n        \"low\": 60,\n        \"high\": 100,\n        \"value\": \"Mui alto\",\n        \"color\": \"dark-green\"\n    }\n]",
          "value": "[\n    {\n        \"low\": 0,\n        \"high\": 15,\n        \"value\": \"Bajo\",\n        \"color\": \"dark-red\"\n    },\n    {\n        \"low\": 15,\n        \"high\": 40,\n        \"value\": \"Medio\",\n        \"color\": \"dark-orange\"\n    },\n    {\n        \"low\": 40,\n        \"high\": 60,\n        \"value\": \"Alto\",\n        \"color\": \"dark-yellow\"\n    },\n    {\n        \"low\": 60,\n        \"high\": 100,\n        \"value\": \"Mui alto\",\n        \"color\": \"dark-green\"\n    }\n]"
        },
        "datasource": "GaliciaSustentable",
        "definition": "select classes from indexes_metadata where index_table_name = '${Index}'",
        "hide": 2,
        "includeAll": false,
        "label": null,
        "multi": false,
        "name": "index_classes",
        "options": [],
        "query": "select classes from indexes_metadata where index_table_name = '${Index}'",
        "refresh": 2,
        "regex": "",
        "skipUrlSync": false,
        "sort": 0,
        "tagValuesQuery": "",
        "tags": [],
        "tagsQuery": "",
        "type": "query",
        "useTags": false
      },
      {
        "allValue": null,
        "current": {
          "selected": false,
          "text": "Autocontención laboral",
          "value": "Autocontención laboral"
        },
        "datasource": "GaliciaSustentable",
        "definition": "select metric_column from indexes_metadata where index_table_name = '${Index}'",
        "hide": 2,
        "includeAll": false,
        "label": null,
        "multi": false,
        "name": "index_metric",
        "options": [],
        "query": "select metric_column from indexes_metadata where index_table_name = '${Index}'",
        "refresh": 1,
        "regex": "",
        "skipUrlSync": false,
        "sort": 0,
        "tagValuesQuery": "",
        "tags": [],
        "tagsQuery": "",
        "type": "query",
        "useTags": false
      }
    ]
  },
  "time": {
    "from": "now-6h",
    "to": "now"
  },
  "timepicker": {
    "hidden": false,
    "refresh_intervals": [
      "1m",
      "6m",
      "1y10s",
      "30s",
      "1m",
      "5m",
      "15m",
      "30m",
      "1h",
      "2h",
      "1d"
    ]
  },
  "timezone": "browser",
  "title": "Detalles de indice",
  "uid": "chRKMVZMz",
  "version": 48
}
